{
  "method_name": "rate_hadamard_value_mse",
  "display_name": "Rate-Hadamard Value MSE",
  "description": "Rate-aware value Hadamard preconditioning: keep K on TurboQuant MSE; at low rate use conservative per-vector value outlier-Hadamard, and at higher rate apply value outlier-Hadamard only in later decoder layers.",
  "results": [
    {
      "baseline": "TurboQuant",
      "method_name": "rate_hadamard_value_mse",
      "kv_bits": 2.5,
      "bit_tag": "2p5",
      "complete": false,
      "num_complete_tasks": 3,
      "num_tasks": 16,
      "category_rows": [
        {
          "category": "SingleQA",
          "complete": false,
          "baseline_score": null,
          "candidate_score": null,
          "delta": null,
          "candidate_cache_ratio": null
        },
        {
          "category": "MultiQA",
          "complete": true,
          "baseline_score": 36.00730828625566,
          "candidate_score": 37.15532909070061,
          "delta": 1.1480208044449565,
          "candidate_cache_ratio": 0.17249459461754968
        },
        {
          "category": "Summarization",
          "complete": false,
          "baseline_score": null,
          "candidate_score": null,
          "delta": null,
          "candidate_cache_ratio": null
        },
        {
          "category": "Few shot",
          "complete": false,
          "baseline_score": null,
          "candidate_score": null,
          "delta": null,
          "candidate_cache_ratio": null
        },
        {
          "category": "Synthetic",
          "complete": false,
          "baseline_score": null,
          "candidate_score": null,
          "delta": null,
          "candidate_cache_ratio": null
        },
        {
          "category": "Code",
          "complete": false,
          "baseline_score": null,
          "candidate_score": null,
          "delta": null,
          "candidate_cache_ratio": null
        }
      ],
      "task_rows": [
        {
          "category": "SingleQA",
          "dataset": "narrativeqa",
          "expected": 200,
          "baseline_records": 200,
          "candidate_records": 0,
          "common_records": 0,
          "complete": false,
          "baseline_score": null,
          "candidate_score": null,
          "delta": null,
          "candidate_cache_ratio": null,
          "candidate_jsonl": "/datasets/liying/projects/turboquant/reproduce/runs/incremental/rate_hadamard_value_mse_narrativeqa_turboquant_2p5_full.jsonl",
          "baseline_jsonl": "/datasets/liying/projects/turboquant/reproduce/runs/table1_official/longbench_narrativeqa_turboquant_2_5bit_all.jsonl"
        },
        {
          "category": "SingleQA",
          "dataset": "qasper",
          "expected": 200,
          "baseline_records": 200,
          "candidate_records": 0,
          "common_records": 0,
          "complete": false,
          "baseline_score": null,
          "candidate_score": null,
          "delta": null,
          "candidate_cache_ratio": null,
          "candidate_jsonl": "/datasets/liying/projects/turboquant/reproduce/runs/incremental/rate_hadamard_value_mse_qasper_turboquant_2p5_full.jsonl",
          "baseline_jsonl": "/datasets/liying/projects/turboquant/reproduce/runs/table1_official/longbench_qasper_turboquant_2_5bit_all.jsonl"
        },
        {
          "category": "SingleQA",
          "dataset": "multifieldqa_en",
          "expected": 150,
          "baseline_records": 150,
          "candidate_records": 0,
          "common_records": 0,
          "complete": false,
          "baseline_score": null,
          "candidate_score": null,
          "delta": null,
          "candidate_cache_ratio": null,
          "candidate_jsonl": "/datasets/liying/projects/turboquant/reproduce/runs/incremental/rate_hadamard_value_mse_multifieldqa_en_turboquant_2p5_full.jsonl",
          "baseline_jsonl": "/datasets/liying/projects/turboquant/reproduce/runs/table1_official/longbench_multifieldqa_en_turboquant_2_5bit_all.jsonl"
        },
        {
          "category": "MultiQA",
          "dataset": "hotpotqa",
          "expected": 200,
          "baseline_records": 200,
          "candidate_records": 200,
          "common_records": 200,
          "complete": true,
          "baseline_score": 44.825020885547204,
          "candidate_score": 49.05160818713452,
          "delta": 4.226587301587315,
          "candidate_cache_ratio": 0.17245545425370812,
          "candidate_jsonl": "/datasets/liying/projects/turboquant/reproduce/runs/incremental/rate_hadamard_value_mse_hotpotqa_turboquant_2p5_full.jsonl",
          "baseline_jsonl": "/datasets/liying/projects/turboquant/reproduce/runs/table1_official/longbench_hotpotqa_turboquant_2_5bit_all.jsonl"
        },
        {
          "category": "MultiQA",
          "dataset": "2wikimqa",
          "expected": 200,
          "baseline_records": 200,
          "candidate_records": 200,
          "common_records": 200,
          "complete": true,
          "baseline_score": 37.95967643467643,
          "candidate_score": 38.87896825396825,
          "delta": 0.9192918192918214,
          "candidate_cache_ratio": 0.17259368457651253,
          "candidate_jsonl": "/datasets/liying/projects/turboquant/reproduce/runs/incremental/rate_hadamard_value_mse_2wikimqa_turboquant_2p5_full.jsonl",
          "baseline_jsonl": "/datasets/liying/projects/turboquant/reproduce/runs/table1_official/longbench_2wikimqa_turboquant_2_5bit_all.jsonl"
        },
        {
          "category": "MultiQA",
          "dataset": "musique",
          "expected": 200,
          "baseline_records": 200,
          "candidate_records": 200,
          "common_records": 200,
          "complete": true,
          "baseline_score": 25.23722753854333,
          "candidate_score": 23.535410830999062,
          "delta": -1.7018167075442676,
          "candidate_cache_ratio": 0.17243464502242842,
          "candidate_jsonl": "/datasets/liying/projects/turboquant/reproduce/runs/incremental/rate_hadamard_value_mse_musique_turboquant_2p5_full.jsonl",
          "baseline_jsonl": "/datasets/liying/projects/turboquant/reproduce/runs/table1_official/longbench_musique_turboquant_2_5bit_all.jsonl"
        },
        {
          "category": "Summarization",
          "dataset": "gov_report",
          "expected": 200,
          "baseline_records": 200,
          "candidate_records": 0,
          "common_records": 0,
          "complete": false,
          "baseline_score": null,
          "candidate_score": null,
          "delta": null,
          "candidate_cache_ratio": null,
          "candidate_jsonl": "/datasets/liying/projects/turboquant/reproduce/runs/incremental/rate_hadamard_value_mse_gov_report_turboquant_2p5_full.jsonl",
          "baseline_jsonl": "/datasets/liying/projects/turboquant/reproduce/runs/table1_official/longbench_gov_report_turboquant_2_5bit_all.jsonl"
        },
        {
          "category": "Summarization",
          "dataset": "qmsum",
          "expected": 200,
          "baseline_records": 200,
          "candidate_records": 0,
          "common_records": 0,
          "complete": false,
          "baseline_score": null,
          "candidate_score": null,
          "delta": null,
          "candidate_cache_ratio": null,
          "candidate_jsonl": "/datasets/liying/projects/turboquant/reproduce/runs/incremental/rate_hadamard_value_mse_qmsum_turboquant_2p5_full.jsonl",
          "baseline_jsonl": "/datasets/liying/projects/turboquant/reproduce/runs/table1_official/longbench_qmsum_turboquant_2_5bit_all.jsonl"
        },
        {
          "category": "Summarization",
          "dataset": "multi_news",
          "expected": 200,
          "baseline_records": 200,
          "candidate_records": 0,
          "common_records": 0,
          "complete": false,
          "baseline_score": null,
          "candidate_score": null,
          "delta": null,
          "candidate_cache_ratio": null,
          "candidate_jsonl": "/datasets/liying/projects/turboquant/reproduce/runs/incremental/rate_hadamard_value_mse_multi_news_turboquant_2p5_full.jsonl",
          "baseline_jsonl": "/datasets/liying/projects/turboquant/reproduce/runs/table1_official/longbench_multi_news_turboquant_2_5bit_all.jsonl"
        },
        {
          "category": "Few shot",
          "dataset": "trec",
          "expected": 200,
          "baseline_records": 200,
          "candidate_records": 0,
          "common_records": 0,
          "complete": false,
          "baseline_score": null,
          "candidate_score": null,
          "delta": null,
          "candidate_cache_ratio": null,
          "candidate_jsonl": "/datasets/liying/projects/turboquant/reproduce/runs/incremental/rate_hadamard_value_mse_trec_turboquant_2p5_full.jsonl",
          "baseline_jsonl": "/datasets/liying/projects/turboquant/reproduce/runs/table1_official/longbench_trec_turboquant_2_5bit_all.jsonl"
        },
        {
          "category": "Few shot",
          "dataset": "triviaqa",
          "expected": 200,
          "baseline_records": 200,
          "candidate_records": 0,
          "common_records": 0,
          "complete": false,
          "baseline_score": null,
          "candidate_score": null,
          "delta": null,
          "candidate_cache_ratio": null,
          "candidate_jsonl": "/datasets/liying/projects/turboquant/reproduce/runs/incremental/rate_hadamard_value_mse_triviaqa_turboquant_2p5_full.jsonl",
          "baseline_jsonl": "/datasets/liying/projects/turboquant/reproduce/runs/table1_official/longbench_triviaqa_turboquant_2_5bit_all.jsonl"
        },
        {
          "category": "Few shot",
          "dataset": "samsum",
          "expected": 200,
          "baseline_records": 200,
          "candidate_records": 0,
          "common_records": 0,
          "complete": false,
          "baseline_score": null,
          "candidate_score": null,
          "delta": null,
          "candidate_cache_ratio": null,
          "candidate_jsonl": "/datasets/liying/projects/turboquant/reproduce/runs/incremental/rate_hadamard_value_mse_samsum_turboquant_2p5_full.jsonl",
          "baseline_jsonl": "/datasets/liying/projects/turboquant/reproduce/runs/table1_official/longbench_samsum_turboquant_2_5bit_all.jsonl"
        },
        {
          "category": "Synthetic",
          "dataset": "passage_retrieval_en",
          "expected": 200,
          "baseline_records": 200,
          "candidate_records": 0,
          "common_records": 0,
          "complete": false,
          "baseline_score": null,
          "candidate_score": null,
          "delta": null,
          "candidate_cache_ratio": null,
          "candidate_jsonl": "/datasets/liying/projects/turboquant/reproduce/runs/incremental/rate_hadamard_value_mse_passage_retrieval_en_turboquant_2p5_full.jsonl",
          "baseline_jsonl": "/datasets/liying/projects/turboquant/reproduce/runs/table1_official/longbench_passage_retrieval_en_turboquant_2_5bit_all.jsonl"
        },
        {
          "category": "Synthetic",
          "dataset": "passage_count",
          "expected": 200,
          "baseline_records": 200,
          "candidate_records": 0,
          "common_records": 0,
          "complete": false,
          "baseline_score": null,
          "candidate_score": null,
          "delta": null,
          "candidate_cache_ratio": null,
          "candidate_jsonl": "/datasets/liying/projects/turboquant/reproduce/runs/incremental/rate_hadamard_value_mse_passage_count_turboquant_2p5_full.jsonl",
          "baseline_jsonl": "/datasets/liying/projects/turboquant/reproduce/runs/table1_official/longbench_passage_count_turboquant_2_5bit_all.jsonl"
        },
        {
          "category": "Code",
          "dataset": "lcc",
          "expected": 500,
          "baseline_records": 500,
          "candidate_records": 0,
          "common_records": 0,
          "complete": false,
          "baseline_score": null,
          "candidate_score": null,
          "delta": null,
          "candidate_cache_ratio": null,
          "candidate_jsonl": "/datasets/liying/projects/turboquant/reproduce/runs/incremental/rate_hadamard_value_mse_lcc_turboquant_2p5_full.jsonl",
          "baseline_jsonl": "/datasets/liying/projects/turboquant/reproduce/runs/table1_official/longbench_lcc_turboquant_2_5bit_all.jsonl"
        },
        {
          "category": "Code",
          "dataset": "repobench-p",
          "expected": 500,
          "baseline_records": 500,
          "candidate_records": 0,
          "common_records": 0,
          "complete": false,
          "baseline_score": null,
          "candidate_score": null,
          "delta": null,
          "candidate_cache_ratio": null,
          "candidate_jsonl": "/datasets/liying/projects/turboquant/reproduce/runs/incremental/rate_hadamard_value_mse_repobench-p_turboquant_2p5_full.jsonl",
          "baseline_jsonl": "/datasets/liying/projects/turboquant/reproduce/runs/table1_official/longbench_repobench-p_turboquant_2_5bit_all.jsonl"
        }
      ],
      "average": {
        "baseline_score": null,
        "candidate_score": null,
        "delta": null,
        "candidate_cache_ratio": null
      }
    },
    {
      "baseline": "TurboQuant",
      "method_name": "rate_hadamard_value_mse",
      "kv_bits": 3.5,
      "bit_tag": "3p5",
      "complete": false,
      "num_complete_tasks": 3,
      "num_tasks": 16,
      "category_rows": [
        {
          "category": "SingleQA",
          "complete": false,
          "baseline_score": null,
          "candidate_score": null,
          "delta": null,
          "candidate_cache_ratio": null
        },
        {
          "category": "MultiQA",
          "complete": true,
          "baseline_score": 43.041737258842524,
          "candidate_score": 43.732611247841135,
          "delta": 0.6908739889986073,
          "candidate_cache_ratio": 0.2344810335765215
        },
        {
          "category": "Summarization",
          "complete": false,
          "baseline_score": null,
          "candidate_score": null,
          "delta": null,
          "candidate_cache_ratio": null
        },
        {
          "category": "Few shot",
          "complete": false,
          "baseline_score": null,
          "candidate_score": null,
          "delta": null,
          "candidate_cache_ratio": null
        },
        {
          "category": "Synthetic",
          "complete": false,
          "baseline_score": null,
          "candidate_score": null,
          "delta": null,
          "candidate_cache_ratio": null
        },
        {
          "category": "Code",
          "complete": false,
          "baseline_score": null,
          "candidate_score": null,
          "delta": null,
          "candidate_cache_ratio": null
        }
      ],
      "task_rows": [
        {
          "category": "SingleQA",
          "dataset": "narrativeqa",
          "expected": 200,
          "baseline_records": 200,
          "candidate_records": 0,
          "common_records": 0,
          "complete": false,
          "baseline_score": null,
          "candidate_score": null,
          "delta": null,
          "candidate_cache_ratio": null,
          "candidate_jsonl": "/datasets/liying/projects/turboquant/reproduce/runs/incremental/rate_hadamard_value_mse_narrativeqa_turboquant_3p5_full.jsonl",
          "baseline_jsonl": "/datasets/liying/projects/turboquant/reproduce/runs/table1_official/longbench_narrativeqa_turboquant_3_5bit_all.jsonl"
        },
        {
          "category": "SingleQA",
          "dataset": "qasper",
          "expected": 200,
          "baseline_records": 200,
          "candidate_records": 0,
          "common_records": 0,
          "complete": false,
          "baseline_score": null,
          "candidate_score": null,
          "delta": null,
          "candidate_cache_ratio": null,
          "candidate_jsonl": "/datasets/liying/projects/turboquant/reproduce/runs/incremental/rate_hadamard_value_mse_qasper_turboquant_3p5_full.jsonl",
          "baseline_jsonl": "/datasets/liying/projects/turboquant/reproduce/runs/table1_official/longbench_qasper_turboquant_3_5bit_all.jsonl"
        },
        {
          "category": "SingleQA",
          "dataset": "multifieldqa_en",
          "expected": 150,
          "baseline_records": 150,
          "candidate_records": 0,
          "common_records": 0,
          "complete": false,
          "baseline_score": null,
          "candidate_score": null,
          "delta": null,
          "candidate_cache_ratio": null,
          "candidate_jsonl": "/datasets/liying/projects/turboquant/reproduce/runs/incremental/rate_hadamard_value_mse_multifieldqa_en_turboquant_3p5_full.jsonl",
          "baseline_jsonl": "/datasets/liying/projects/turboquant/reproduce/runs/table1_official/longbench_multifieldqa_en_turboquant_3_5bit_all.jsonl"
        },
        {
          "category": "MultiQA",
          "dataset": "hotpotqa",
          "expected": 200,
          "baseline_records": 200,
          "candidate_records": 200,
          "common_records": 200,
          "complete": true,
          "baseline_score": 54.648157398157394,
          "candidate_score": 56.00264457764457,
          "delta": 1.3544871794871725,
          "candidate_cache_ratio": 0.2344503233445327,
          "candidate_jsonl": "/datasets/liying/projects/turboquant/reproduce/runs/incremental/rate_hadamard_value_mse_hotpotqa_turboquant_3p5_full.jsonl",
          "baseline_jsonl": "/datasets/liying/projects/turboquant/reproduce/runs/table1_official/longbench_hotpotqa_turboquant_3_5bit_all.jsonl"
        },
        {
          "category": "MultiQA",
          "dataset": "2wikimqa",
          "expected": 200,
          "baseline_records": 200,
          "candidate_records": 200,
          "common_records": 200,
          "complete": true,
          "baseline_score": 44.46666666666667,
          "candidate_score": 46.087770562770565,
          "delta": 1.6211038961038966,
          "candidate_cache_ratio": 0.23455011985628804,
          "candidate_jsonl": "/datasets/liying/projects/turboquant/reproduce/runs/incremental/rate_hadamard_value_mse_2wikimqa_turboquant_3p5_full.jsonl",
          "baseline_jsonl": "/datasets/liying/projects/turboquant/reproduce/runs/table1_official/longbench_2wikimqa_turboquant_3_5bit_all.jsonl"
        },
        {
          "category": "MultiQA",
          "dataset": "musique",
          "expected": 200,
          "baseline_records": 200,
          "candidate_records": 200,
          "common_records": 200,
          "complete": true,
          "baseline_score": 30.010387711703505,
          "candidate_score": 29.107418603108258,
          "delta": -0.9029691085952471,
          "candidate_cache_ratio": 0.2344426575287438,
          "candidate_jsonl": "/datasets/liying/projects/turboquant/reproduce/runs/incremental/rate_hadamard_value_mse_musique_turboquant_3p5_full.jsonl",
          "baseline_jsonl": "/datasets/liying/projects/turboquant/reproduce/runs/table1_official/longbench_musique_turboquant_3_5bit_all.jsonl"
        },
        {
          "category": "Summarization",
          "dataset": "gov_report",
          "expected": 200,
          "baseline_records": 200,
          "candidate_records": 0,
          "common_records": 0,
          "complete": false,
          "baseline_score": null,
          "candidate_score": null,
          "delta": null,
          "candidate_cache_ratio": null,
          "candidate_jsonl": "/datasets/liying/projects/turboquant/reproduce/runs/incremental/rate_hadamard_value_mse_gov_report_turboquant_3p5_full.jsonl",
          "baseline_jsonl": "/datasets/liying/projects/turboquant/reproduce/runs/table1_official/longbench_gov_report_turboquant_3_5bit_all.jsonl"
        },
        {
          "category": "Summarization",
          "dataset": "qmsum",
          "expected": 200,
          "baseline_records": 200,
          "candidate_records": 0,
          "common_records": 0,
          "complete": false,
          "baseline_score": null,
          "candidate_score": null,
          "delta": null,
          "candidate_cache_ratio": null,
          "candidate_jsonl": "/datasets/liying/projects/turboquant/reproduce/runs/incremental/rate_hadamard_value_mse_qmsum_turboquant_3p5_full.jsonl",
          "baseline_jsonl": "/datasets/liying/projects/turboquant/reproduce/runs/table1_official/longbench_qmsum_turboquant_3_5bit_all.jsonl"
        },
        {
          "category": "Summarization",
          "dataset": "multi_news",
          "expected": 200,
          "baseline_records": 200,
          "candidate_records": 0,
          "common_records": 0,
          "complete": false,
          "baseline_score": null,
          "candidate_score": null,
          "delta": null,
          "candidate_cache_ratio": null,
          "candidate_jsonl": "/datasets/liying/projects/turboquant/reproduce/runs/incremental/rate_hadamard_value_mse_multi_news_turboquant_3p5_full.jsonl",
          "baseline_jsonl": "/datasets/liying/projects/turboquant/reproduce/runs/table1_official/longbench_multi_news_turboquant_3_5bit_all.jsonl"
        },
        {
          "category": "Few shot",
          "dataset": "trec",
          "expected": 200,
          "baseline_records": 200,
          "candidate_records": 0,
          "common_records": 0,
          "complete": false,
          "baseline_score": null,
          "candidate_score": null,
          "delta": null,
          "candidate_cache_ratio": null,
          "candidate_jsonl": "/datasets/liying/projects/turboquant/reproduce/runs/incremental/rate_hadamard_value_mse_trec_turboquant_3p5_full.jsonl",
          "baseline_jsonl": "/datasets/liying/projects/turboquant/reproduce/runs/table1_official/longbench_trec_turboquant_3_5bit_all.jsonl"
        },
        {
          "category": "Few shot",
          "dataset": "triviaqa",
          "expected": 200,
          "baseline_records": 200,
          "candidate_records": 0,
          "common_records": 0,
          "complete": false,
          "baseline_score": null,
          "candidate_score": null,
          "delta": null,
          "candidate_cache_ratio": null,
          "candidate_jsonl": "/datasets/liying/projects/turboquant/reproduce/runs/incremental/rate_hadamard_value_mse_triviaqa_turboquant_3p5_full.jsonl",
          "baseline_jsonl": "/datasets/liying/projects/turboquant/reproduce/runs/table1_official/longbench_triviaqa_turboquant_3_5bit_all.jsonl"
        },
        {
          "category": "Few shot",
          "dataset": "samsum",
          "expected": 200,
          "baseline_records": 200,
          "candidate_records": 0,
          "common_records": 0,
          "complete": false,
          "baseline_score": null,
          "candidate_score": null,
          "delta": null,
          "candidate_cache_ratio": null,
          "candidate_jsonl": "/datasets/liying/projects/turboquant/reproduce/runs/incremental/rate_hadamard_value_mse_samsum_turboquant_3p5_full.jsonl",
          "baseline_jsonl": "/datasets/liying/projects/turboquant/reproduce/runs/table1_official/longbench_samsum_turboquant_3_5bit_all.jsonl"
        },
        {
          "category": "Synthetic",
          "dataset": "passage_retrieval_en",
          "expected": 200,
          "baseline_records": 200,
          "candidate_records": 0,
          "common_records": 0,
          "complete": false,
          "baseline_score": null,
          "candidate_score": null,
          "delta": null,
          "candidate_cache_ratio": null,
          "candidate_jsonl": "/datasets/liying/projects/turboquant/reproduce/runs/incremental/rate_hadamard_value_mse_passage_retrieval_en_turboquant_3p5_full.jsonl",
          "baseline_jsonl": "/datasets/liying/projects/turboquant/reproduce/runs/table1_official/longbench_passage_retrieval_en_turboquant_3_5bit_all.jsonl"
        },
        {
          "category": "Synthetic",
          "dataset": "passage_count",
          "expected": 200,
          "baseline_records": 200,
          "candidate_records": 0,
          "common_records": 0,
          "complete": false,
          "baseline_score": null,
          "candidate_score": null,
          "delta": null,
          "candidate_cache_ratio": null,
          "candidate_jsonl": "/datasets/liying/projects/turboquant/reproduce/runs/incremental/rate_hadamard_value_mse_passage_count_turboquant_3p5_full.jsonl",
          "baseline_jsonl": "/datasets/liying/projects/turboquant/reproduce/runs/table1_official/longbench_passage_count_turboquant_3_5bit_all.jsonl"
        },
        {
          "category": "Code",
          "dataset": "lcc",
          "expected": 500,
          "baseline_records": 500,
          "candidate_records": 0,
          "common_records": 0,
          "complete": false,
          "baseline_score": null,
          "candidate_score": null,
          "delta": null,
          "candidate_cache_ratio": null,
          "candidate_jsonl": "/datasets/liying/projects/turboquant/reproduce/runs/incremental/rate_hadamard_value_mse_lcc_turboquant_3p5_full.jsonl",
          "baseline_jsonl": "/datasets/liying/projects/turboquant/reproduce/runs/table1_official/longbench_lcc_turboquant_3_5bit_all.jsonl"
        },
        {
          "category": "Code",
          "dataset": "repobench-p",
          "expected": 500,
          "baseline_records": 500,
          "candidate_records": 0,
          "common_records": 0,
          "complete": false,
          "baseline_score": null,
          "candidate_score": null,
          "delta": null,
          "candidate_cache_ratio": null,
          "candidate_jsonl": "/datasets/liying/projects/turboquant/reproduce/runs/incremental/rate_hadamard_value_mse_repobench-p_turboquant_3p5_full.jsonl",
          "baseline_jsonl": "/datasets/liying/projects/turboquant/reproduce/runs/table1_official/longbench_repobench-p_turboquant_3_5bit_all.jsonl"
        }
      ],
      "average": {
        "baseline_score": null,
        "candidate_score": null,
        "delta": null,
        "candidate_cache_ratio": null
      }
    }
  ]
}
